coover/Beatmap.py
coover/OsuAPIWrapper.py
coover/OsuApiV2.py
coover/__init__.py
coover/replayparser.py
coover-0.1.2.dist-info/LICENSE
coover-0.1.2.dist-info/METADATA
coover-0.1.2.dist-info/WHEEL
coover-0.1.2.dist-info/top_level.txt
coover-0.1.2.dist-info/RECORD
