Metadata-Version: 2.1
Name: coover
Version: 0.1.2
Summary: Using this package for code that I tend to rewrite a lot
Home-page: https://github.com/coverosu/coover
Author: coverosu
Author-email: ImEasyCJ@gmail.com
License: UNKNOWN
Platform: UNKNOWN
Classifier: Programming Language :: Python :: 3
Classifier: License :: OSI Approved :: MIT License
Classifier: Operating System :: OS Independent
Requires-Python: >=3.6
